class_7zip_arch.cp38-win_amd64.pyd
class_7zip_arch/7z.dll
class_7zip_arch/Archive.cpp
class_7zip_arch/Archive.h
class_7zip_arch/_main.cpp
class_7zip_arch/class7zarch.cpp
class_7zip_arch/class7zarch.h
class_7zip_arch/class7zarchiter.cpp
class_7zip_arch/class7zarchiter.h
class_7zip_arch/misc.cpp
class_7zip_arch/misc.h
class_7zip_arch/libs7z/bit7z64.lib
class_7zip_arch/libs7z/bit7z64_d.lib
class_7zip_arch/libs7z/include/bit7z.hpp
class_7zip_arch/libs7z/include/bit7zlibrary.hpp
class_7zip_arch/libs7z/include/bitarchivecreator.hpp
class_7zip_arch/libs7z/include/bitarchivehandler.hpp
class_7zip_arch/libs7z/include/bitarchiveinfo.hpp
class_7zip_arch/libs7z/include/bitarchiveitem.hpp
class_7zip_arch/libs7z/include/bitarchiveopener.hpp
class_7zip_arch/libs7z/include/bitcompressionlevel.hpp
class_7zip_arch/libs7z/include/bitcompressionmethod.hpp
class_7zip_arch/libs7z/include/bitcompressor.hpp
class_7zip_arch/libs7z/include/bitexception.hpp
class_7zip_arch/libs7z/include/bitextractor.hpp
class_7zip_arch/libs7z/include/bitformat.hpp
class_7zip_arch/libs7z/include/bitguids.hpp
class_7zip_arch/libs7z/include/bitinputarchive.hpp
class_7zip_arch/libs7z/include/bitmemcompressor.hpp
class_7zip_arch/libs7z/include/bitmemextractor.hpp
class_7zip_arch/libs7z/include/bitpropvariant.hpp
class_7zip_arch/libs7z/include/bitstreamcompressor.hpp
class_7zip_arch/libs7z/include/bitstreamextractor.hpp
class_7zip_arch/libs7z/include/bittypes.hpp
class_7zip_arch/test/cats.lzh
class_7zip_arch/test/test.py
class_7zip_arch/test/test_2.py
class_7zip_arch/test/test_3.py
class_7zip_arch-1.3.2.dist-info/LICENSE
class_7zip_arch-1.3.2.dist-info/METADATA
class_7zip_arch-1.3.2.dist-info/WHEEL
class_7zip_arch-1.3.2.dist-info/top_level.txt
class_7zip_arch-1.3.2.dist-info/RECORD
