Metadata-Version: 2.1
Name: class-7zip-arch
Version: 1.3.2
Summary: Python extension for using 7zip.dll in memory (Example in test/test.py)
Home-page: https://github.com/aver007/class_7zip_arch
License: UNKNOWN
Platform: UNKNOWN
Requires-Python: >=3.8, <4
